decisiveml/__init__.py
decisiveml/helpers.py
decisiveml/indicators.py
decisiveml/montecarlo.py
decisiveml/trendscanning.py
decisiveml-0.0.3.dist-info/LICENSE.txt
decisiveml-0.0.3.dist-info/WHEEL
decisiveml-0.0.3.dist-info/METADATA
decisiveml-0.0.3.dist-info/RECORD
